[{"car_name": "E-Class", "sub_name": "E300 4MATIC", "quentity": "8,806"}, {"car_name": "E-Class", "sub_name": "E220d", "quentity": "6,530"}, {"car_name": "E-Class", "sub_name": "E300", "quentity": "6,299"}, {"car_name": "E-Class", "sub_name": "E200", "quentity": "4,737"}, {"car_name": "E-Class", "sub_name": "E220d 4MATIC", "quentity": "4,645"}, {"car_name": "E-Class", "sub_name": "E400 4MATIC", "quentity": "1,398"}, {"car_name": "E-Class", "sub_name": "E220d Coupe", "quentity": "957"}, {"car_name": "E-Class", "sub_name": "E350d", "quentity": "756"}, {"car_name": "E-Class", "sub_name": "E400 4MATIC Coupe", "quentity": "330"}, {"car_name": "E-Class", "sub_name": "E43 4MATIC AMG", "quentity": "276"}, {"car_name": "E-Class", "sub_name": "E63 4MATIC+ AMG", "quentity": "3"}, {"car_name": "E-Class", "sub_name": "E63 4MATIC+ AMG", "quentity": "3"}, {"car_name": "C-Class", "sub_name": "C200", "quentity": "4,834"}, {"car_name": "C-Class", "sub_name": "C220d", "quentity": "2,593"}, {"car_name": "C-Class", "sub_name": "C200 Cabriolet", "quentity": "901"}, {"car_name": "C-Class", "sub_name": "C200d", "quentity": "742"}, {"car_name": "C-Class", "sub_name": "C220d 4MATIC", "quentity": "577"}, {"car_name": "C-Class", "sub_name": "C200 Coupe", "quentity": "369"}, {"car_name": "C-Class", "sub_name": "C250d 4MATIC", "quentity": "355"}, {"car_name": "C-Class", "sub_name": "C43 4MATIC AMG", "quentity": "204"}, {"car_name": "C-Class", "sub_name": "C220d Coupe", "quentity": "137"}, {"car_name": "C-Class", "sub_name": "C63 Coupe AMG", "quentity": "119"}, {"car_name": "C-Class", "sub_name": "C63 Cabriolet AMG", "quentity": "71"}, {"car_name": "C-Class", "sub_name": "C63 AMG", "quentity": "71"}, {"car_name": "C-Class", "sub_name": " C63 S AMG", "quentity": "31"}, {"car_name": "C-Class", "sub_name": "C63 S Coupe AMG", "quentity": "27"}, {"car_name": "C-Class", "sub_name": "C220d 4MATIC Estate", "quentity": "7"}, {"car_name": "C-Class", "sub_name": "C450 4MATIC AMG", "quentity": "2"}, {"car_name": "C-Class", "sub_name": "C450 4MATIC AMG", "quentity": "2"}, {"car_name": "S-Class", "sub_name": "S350d 4MATIC", "quentity": "2,923"}, {"car_name": "S-Class", "sub_name": "S500 4MATIC", "quentity": "754"}, {"car_name": "S-Class", "sub_name": "S400 4MATIC", "quentity": "399"}, {"car_name": "S-Class", "sub_name": "S350d", "quentity": "300"}, {"car_name": "S-Class", "sub_name": "S63 4MATIC Long AMG", "quentity": "188"}, {"car_name": "S-Class", "sub_name": "S63 4MATIC Coupe AMG", "quentity": "85"}, {"car_name": "S-Class", "sub_name": "S400 4MATIC Coupe", "quentity": "57"}, {"car_name": "S-Class", "sub_name": "S63 4MATIC Cabriolet AMG", "quentity": "54"}, {"car_name": "S-Class", "sub_name": "S500", "quentity": "22"}, {"car_name": "S-Class", "sub_name": "S65 Long AMG", "quentity": "16"}, {"car_name": "S-Class", "sub_name": "S65 Coupe AMG", "quentity": "13"}, {"car_name": "S-Class", "sub_name": "S400", "quentity": "9"}, {"car_name": "S-Class", "sub_name": "S63 4MATIC AMG", "quentity": "5"}, {"car_name": "S-Class", "sub_name": "S63 4MATIC Coupe AMG", "quentity": "4"}, {"car_name": "S-Class", "sub_name": "S350 BlueTEC 4MATIC", "quentity": "1"}, {"car_name": "S-Class", "sub_name": "S600", "quentity": "1"}, {"car_name": "S-Class", "sub_name": "S600", "quentity": "1"}, {"car_name": "GLC-Class", "sub_name": "GLC220d 4MATIC Coupe", "quentity": "2,319"}, {"car_name": "GLC-Class", "sub_name": "GLC220d 4MATIC", "quentity": "1,529"}, {"car_name": "GLC-Class", "sub_name": "GLC250d 4MATIC Coupe", "quentity": "227"}, {"car_name": "GLC-Class", "sub_name": "AMG GLC43 4MATIC", "quentity": "226"}, {"car_name": "GLC-Class", "sub_name": "GLC250d 4MATIC", "quentity": "216"}, {"car_name": "GLC-Class", "sub_name": "AMG GLC43 4MATIC Coupe", "quentity": "206"}, {"car_name": "GLC-Class", "sub_name": "AMG GLC43 4MATIC Coupe", "quentity": "206"}, {"car_name": "GLE-Class", "sub_name": "GLE350d 4MATIC Coupe", "quentity": "1,951"}, {"car_name": "GLE-Class", "sub_name": "GLE350d 4MATIC", "quentity": "1,253"}, {"car_name": "GLE-Class", "sub_name": "GLE250d 4MATIC", "quentity": "332"}, {"car_name": "GLE-Class", "sub_name": "AMG GLE63 S 4MATIC Coupe", "quentity": "162"}, {"car_name": "GLE-Class", "sub_name": "GLE63 4MATIC AMG", "quentity": "115"}, {"car_name": "GLE-Class", "sub_name": "GLE63 4MATIC AMG", "quentity": "115"}, {"car_name": "CLA-Class", "sub_name": "CLA250 4MATIC", "quentity": "1,655"}, {"car_name": "CLA-Class", "sub_name": "CLA220", "quentity": "1,121"}, {"car_name": "CLA-Class", "sub_name": "CLA 45 4MATIC AMG", "quentity": "304"}, {"car_name": "CLA-Class", "sub_name": "CLA200d", "quentity": "2"}, {"car_name": "CLA-Class", "sub_name": "CLA200d", "quentity": "2"}, {"car_name": "CLS-Class", "sub_name": "CLS250d 4MATIC", "quentity": "1,528"}, {"car_name": "CLS-Class", "sub_name": "CLS400", "quentity": "636"}, {"car_name": "CLS-Class", "sub_name": "CLS63 4MATIC AMG", "quentity": "79"}, {"car_name": "CLS-Class", "sub_name": "CLS63 S 4MATIC AMG", "quentity": "55"}, {"car_name": "CLS-Class", "sub_name": "CLS350d 4MATIC", "quentity": "14"}, {"car_name": "CLS-Class", "sub_name": "CLS350d 4MATIC", "quentity": "14"}, {"car_name": "S-Class", "sub_name": "S560 4MATIC Long", "quentity": "703"}, {"car_name": "S-Class", "sub_name": "S450 4MATIC Long", "quentity": "703"}, {"car_name": "S-Class", "sub_name": "S400d 4MATIC Long", "quentity": "699"}, {"car_name": "S-Class", "sub_name": "AMG S63 4MATIC+ L", "quentity": "129"}, {"car_name": "S-Class", "sub_name": "S450 Long", "quentity": "71"}, {"car_name": "S-Class", "sub_name": "S450 Long", "quentity": "71"}, {"car_name": "GLA-Class", "sub_name": "GLA220", "quentity": "1,972"}, {"car_name": "GLA-Class", "sub_name": "AMG GLA45 4MATIC", "quentity": "149"}, {"car_name": "GLA-Class", "sub_name": "GLA250 4MATIC", "quentity": "90"}, {"car_name": "GLA-Class", "sub_name": "GLA250 4MATIC", "quentity": "90"}, {"car_name": "E-Class", "sub_name": "E200", "quentity": "1,877"}, {"car_name": "E-Class", "sub_name": "E400 4MATIC", "quentity": "157"}, {"car_name": "E-Class", "sub_name": "E200 Cabriolet", "quentity": "63"}, {"car_name": "E-Class", "sub_name": "E200 Coupe", "quentity": "24"}, {"car_name": "E-Class", "sub_name": "E400 Coupe", "quentity": "2"}, {"car_name": "E-Class", "sub_name": "E400 Cabriolet", "quentity": "1"}, {"car_name": "E-Class", "sub_name": "E400 Cabriolet", "quentity": "1"}, {"car_name": "A-Class", "sub_name": "A200", "quentity": "1,385"}, {"car_name": "A-Class", "sub_name": "A45 AMG 4MATIC", "quentity": "411"}, {"car_name": "A-Class", "sub_name": "A45 AMG 4MATIC", "quentity": "411"}, {"car_name": "GLS-Class", "sub_name": "GLS350d 4MATIC", "quentity": "512"}, {"car_name": "GLS-Class", "sub_name": "GLS500 4MATIC", "quentity": "362"}, {"car_name": "GLS-Class", "sub_name": "GLS500 4MATIC", "quentity": "362"}, {"car_name": "GLA-Class", "sub_name": "GLA200d", "quentity": "513"}, {"car_name": "GLA-Class", "sub_name": "GLA200d 4MATIC", "quentity": "181"}, {"car_name": "GLA-Class", "sub_name": "GLA45 AMG 4MATIC", "quentity": "63"}, {"car_name": "GLA-Class", "sub_name": "GLA45 AMG 4MATIC", "quentity": "63"}, {"car_name": "B-class", "sub_name": "B200d", "quentity": "395"}, {"car_name": "B-class", "sub_name": "B220", "quentity": "81"}, {"car_name": "B-class", "sub_name": "B200 CDI", "quentity": "15"}, {"car_name": "B-class", "sub_name": "B200 CDI", "quentity": "15"}, {"car_name": "Maybach", "sub_name": "S560 4MATIC (2018)", "quentity": "282"}, {"car_name": "Maybach", "sub_name": "S500 4MATIC", "quentity": "155"}, {"car_name": "Maybach", "sub_name": "S600", "quentity": "30"}, {"car_name": "Maybach", "sub_name": "S600", "quentity": "30"}, {"car_name": "G-Class", "sub_name": "G350d", "quentity": "216"}, {"car_name": "G-Class", "sub_name": "G63 AMG (2017)", "quentity": "154"}, {"car_name": "G-Class", "sub_name": "G63 AMG", "quentity": "8"}, {"car_name": "G-Class", "sub_name": "G65 AMG", "quentity": "4"}, {"car_name": "G-Class", "sub_name": "G65 AMG", "quentity": "4"}, {"car_name": "SLC-Class", "sub_name": "SLC200", "quentity": "239"}, {"car_name": "SLC-Class", "sub_name": "SLC43 AMG", "quentity": "108"}, {"car_name": "SLC-Class", "sub_name": "SLC43 AMG", "quentity": "108"}, {"car_name": "SL-Class", "sub_name": "SL400", "quentity": "53"}, {"car_name": "SL-Class", "sub_name": "SL63 AMG", "quentity": "5"}, {"car_name": "SL-Class", "sub_name": "SL63 AMG", "quentity": "5"}, {"car_name": "AMG GT", "sub_name": "GT AMG", "quentity": "16"}, {"car_name": "AMG GT", "sub_name": "GT S AMG", "quentity": "2"}, {"car_name": "AMG GT", "sub_name": "GT S AMG", "quentity": "2"}]