[{"car_name": "Cayenne", "sub_name": "Cayenne Coupe", "quentity": "928"}, {"car_name": "Cayenne", "sub_name": "Cayenne", "quentity": "858"}, {"car_name": "Cayenne", "sub_name": "Cayenne E-Hybrid Coupe", "quentity": "193"}, {"car_name": "Cayenne", "sub_name": "Cayenne E-Hybrid", "quentity": "181"}, {"car_name": "Cayenne", "sub_name": "Cayenne Turbo Coupe", "quentity": "49"}, {"car_name": "Cayenne", "sub_name": "Cayenne Turbo", "quentity": "40"}, {"car_name": "Cayenne", "sub_name": "Cayenne Turbo", "quentity": "40"}, {"car_name": "Taycan", "sub_name": "Taycan 4S", "quentity": "620"}, {"car_name": "Taycan", "sub_name": "Taycan Turbo S", "quentity": "35"}, {"car_name": "Taycan", "sub_name": "Taycan Turbo S", "quentity": "35"}, {"car_name": "911", "sub_name": "3.0  Carrera 4S Cabriolet", "quentity": "92"}, {"car_name": "911", "sub_name": "3.0  Carrera 4S", "quentity": "84"}, {"car_name": "911", "sub_name": "3.0 Carrera S Cabriolet", "quentity": "47"}, {"car_name": "911", "sub_name": "3.8 Turbo S Cabriolet", "quentity": "46"}, {"car_name": "911", "sub_name": "3.0 Carrera Coupe", "quentity": "40"}, {"car_name": "911", "sub_name": "3.8 Turbo S", "quentity": "39"}, {"car_name": "911", "sub_name": "3.0 Carrera S Coupe", "quentity": "38"}, {"car_name": "911", "sub_name": "3.0 Carrera Cabriolet", "quentity": "35"}, {"car_name": "911", "sub_name": "3.0 Carrera 4", "quentity": "25"}, {"car_name": "911", "sub_name": "3.0 Targa 4S", "quentity": "23"}, {"car_name": "911", "sub_name": "3.0 Carrera 4 Cabriolet", "quentity": "20"}, {"car_name": "911", "sub_name": "3.0 Targa 4", "quentity": "11"}, {"car_name": "911", "sub_name": "3.0 Targa 4", "quentity": "11"}, {"car_name": "The new Panamera", "sub_name": "Panamera 4", "quentity": "296"}, {"car_name": "The new Panamera", "sub_name": "Panamera GTS", "quentity": "80"}, {"car_name": "The new Panamera", "sub_name": "Panamera 4 Executive", "quentity": "31"}, {"car_name": "The new Panamera", "sub_name": "Panamera Turbo S", "quentity": "4"}, {"car_name": "The new Panamera", "sub_name": "Panamera 4 E-Hybrid", "quentity": "3"}, {"car_name": "The new Panamera", "sub_name": "Panamera 4 E-Hybrid", "quentity": "3"}, {"car_name": "Macan", "sub_name": "2.0 Macan", "quentity": "165"}, {"car_name": "Macan", "sub_name": "Macan GTS", "quentity": "124"}, {"car_name": "Macan", "sub_name": "Macan GTS", "quentity": "124"}, {"car_name": "718 Boxster", "sub_name": "4.0 Boxster GTS", "quentity": "184"}, {"car_name": "718 Boxster", "sub_name": "2.0 Boxster", "quentity": "17"}, {"car_name": "718 Boxster", "sub_name": "2.5 Boxster S", "quentity": "16"}, {"car_name": "718 Boxster", "sub_name": "2.5 Boxster S", "quentity": "16"}, {"car_name": "718 Cayman", "sub_name": "4.0 Cayman GTS", "quentity": "44"}, {"car_name": "718 Cayman", "sub_name": "2.5 Cayman S", "quentity": "20"}, {"car_name": "718 Cayman", "sub_name": "2.0 Cayman", "quentity": "6"}, {"car_name": "718 Cayman", "sub_name": "2.0 Cayman", "quentity": "6"}, {"car_name": "Panamera", "sub_name": "4.0 Panamera GTS", "quentity": "3"}, {"car_name": "Panamera", "sub_name": "3.0 Panamera 4", "quentity": "1"}, {"car_name": "Panamera", "sub_name": "3.0 Panamera 4", "quentity": "1"}]