[{"car_name": "Huracan", "sub_name": "5.2 LP580-2 Spyder", "quentity": "6"}, {"car_name": "Huracan", "sub_name": "5.2 Performante", "quentity": "4"}, {"car_name": "Huracan", "sub_name": "5.2 LP580-2 Coupe", "quentity": "3"}, {"car_name": "Huracan", "sub_name": "5.2 LP610-4 Spyder", "quentity": "2"}, {"car_name": "Huracan", "sub_name": "5.2 Performante Spyder", "quentity": "2"}, {"car_name": "Huracan", "sub_name": "5.2 LP610-4 Coupe", "quentity": "1"}, {"car_name": "Huracan", "sub_name": "5.2 LP610-4 Coupe", "quentity": "1"}]